{
"type": "FeatureCollection",
"name": "airport",
"crs": { "type": "name", "properties": { "name": "urn:ogc:def:crs:OGC:1.3:CRS84" } },
"features": [
{ "type": "Feature", "properties": { "id": null }, "geometry": { "type": "Point", "coordinates": [ -73.875232346625353, 40.77877747881174 ] } }
]
}
